llm_switch/__init__.py
llm_switch/config.py
llm_switch/exceptions.py
llm_switch/core/__init__.py
llm_switch/core/base.py
llm_switch/core/factory.py
llm_switch/core/response.py
llm_switch/core/service.py
llm_switch/providers/__init__.py
llm_switch/providers/anthropic.py
llm_switch/providers/azure_openai.py
llm_switch/providers/deepseek.py
llm_switch/providers/google.py
llm_switch/providers/huggingface.py
llm_switch/providers/openai.py
llm_switch/providers/xai.py
llm_switch-0.1.1.dist-info/licenses/LICENSE
tests/__init__.py
tests/test_config.py
tests/test_service.py
llm_switch-0.1.1.dist-info/METADATA
llm_switch-0.1.1.dist-info/WHEEL
llm_switch-0.1.1.dist-info/top_level.txt
llm_switch-0.1.1.dist-info/RECORD
